Workbook

Sheet Overview
A1: Ironwood Construction Co. - Business Plan
A2: Consolidated quarterly P&L. Every figure is pulled by formula from the detail tabs - flex those and this view follows.
A3: Quarter | B3: Q1 2026 | C3: Q2 2026 | D3: Q3 2026 | E3: Q4 2026 | F3: Q1 2027 | G3: Q2 2027 | H3: Q3 2027 | I3: Q4 2027
A4: Residential revenue | B4: ='Residential'!B6 | C4: ='Residential'!C6 | D4: ='Residential'!D6 | E4: ='Residential'!E6 | F4: ='Residential'!F6 | G4: ='Residential'!G6 | H4: ='Residential'!H6 | I4: ='Residential'!I6
A5: Commercial revenue | B5: ='Commercial'!B10 | C5: ='Commercial'!C10 | D5: ='Commercial'!D10 | E5: ='Commercial'!E10 | F5: ='Commercial'!F10 | G5: ='Commercial'!G10 | H5: ='Commercial'!H10 | I5: ='Commercial'!I10
A6: Total revenue | B6: =B4+B5 | C6: =C4+C5 | D6: =D4+D5 | E6: =E4+E5 | F6: =F4+F5 | G6: =G4+G5 | H6: =H4+H5 | I6: =I4+I5
A8: Labour | B8: ='Labor'!B8 | C8: ='Labor'!C8 | D8: ='Labor'!D8 | E8: ='Labor'!E8 | F8: ='Labor'!F8 | G8: ='Labor'!G8 | H8: ='Labor'!H8 | I8: ='Labor'!I8
A9: Equipment | B9: ='Equipment'!B7 | C9: ='Equipment'!C7 | D9: ='Equipment'!D7 | E9: ='Equipment'!E7 | F9: ='Equipment'!F7 | G9: ='Equipment'!G7 | H9: ='Equipment'!H7 | I9: ='Equipment'!I7
A10: Materials | B10: ='Materials'!B8 | C10: ='Materials'!C8 | D10: ='Materials'!D8 | E10: ='Materials'!E8 | F10: ='Materials'!F8 | G10: ='Materials'!G8 | H10: ='Materials'!H8 | I10: ='Materials'!I8
A11: Overhead | B11: ='Overhead'!B9 | C11: ='Overhead'!C9 | D11: ='Overhead'!D9 | E11: ='Overhead'!E9 | F11: ='Overhead'!F9 | G11: ='Overhead'!G9 | H11: ='Overhead'!H9 | I11: ='Overhead'!I9
A12: Total costs | B12: =B8+B9+B10+B11 | C12: =C8+C9+C10+C11 | D12: =D8+D9+D10+D11 | E12: =E8+E9+E10+E11 | F12: =F8+F9+F10+F11 | G12: =G8+G9+G10+G11 | H12: =H8+H9+H10+H11 | I12: =I8+I9+I10+I11
A14: Gross profit | B14: =B6-B8-B9-B10 | C14: =C6-C8-C9-C10 | D14: =D6-D8-D9-D10 | E14: =E6-E8-E9-E10 | F14: =F6-F8-F9-F10 | G14: =G6-G8-G9-G10 | H14: =H6-H8-H9-H10 | I14: =I6-I8-I9-I10
A15: Operating profit | B15: =B6-B12 | C15: =C6-C12 | D15: =D6-D12 | E15: =E6-E12 | F15: =F6-F12 | G15: =G6-G12 | H15: =H6-H12 | I15: =I6-I12
A16: Operating margin | B16: =B15/B6 | C16: =C15/C6 | D16: =D15/D6 | E16: =E15/E6 | F16: =F15/F6 | G16: =G15/G6 | H16: =H15/H6 | I16: =I15/I6
A18: Cash balance | B18: =3200000+B15+0 | C18: =B18+C15+0 | D18: =C18+D15+1500000 | E18: =D18+E15+0 | F18: =E18+F15+0 | G18: =F18+G15+0 | H18: =G18+H15+0 | I18: =H18+I15+0

Sheet Residential
A1: Ironwood Construction Co. - Residential
A2: Single-family homes and townhomes. Revenue is recognised on completion; all figures are per quarter.
A3: Quarter | B3: Q1 2026 | C3: Q2 2026 | D3: Q3 2026 | E3: Q4 2026 | F3: Q1 2027 | G3: Q2 2027 | H3: Q3 2027 | I3: Q4 2027
A4: Homes completed | B4: 8 | C4: 10 | D4: 11 | E4: 13 | F4: 15 | G4: 16 | H4: 18 | I4: 20
A5: Avg contract value | B5: 420000 | C5: 420000 | D5: 435000 | E5: 435000 | F5: 450000 | G5: 450000 | H5: 465000 | I5: 465000
A6: Revenue | B6: =B4*B5 | C6: =C4*C5 | D6: =D4*D5 | E6: =E4*E5 | F6: =F4*F5 | G6: =G4*G5 | H6: =H4*H5 | I6: =I4*I5

Sheet Commercial
A1: Ironwood Construction Co. - Commercial
A2: Commercial contracts across three project classes. Revenue = projects in progress this quarter x average contract value.
A3: Quarter | B3: Q1 2026 | C3: Q2 2026 | D3: Q3 2026 | E3: Q4 2026 | F3: Q1 2027 | G3: Q2 2027 | H3: Q3 2027 | I3: Q4 2027
A4: Retail fit-out projects | B4: 3 | C4: 3 | D4: 4 | E4: 4 | F4: 5 | G4: 5 | H4: 6 | I4: 6
A5: Retail avg value | B5: 280000 | C5: 280000 | D5: 280000 | E5: 280000 | F5: 280000 | G5: 280000 | H5: 280000 | I5: 280000
A6: Office build projects | B6: 1 | C6: 1 | D6: 2 | E6: 2 | F6: 2 | G6: 3 | H6: 3 | I6: 4
A7: Office avg value | B7: 1800000 | C7: 1800000 | D7: 1800000 | E7: 1800000 | F7: 1800000 | G7: 1800000 | H7: 1800000 | I7: 1800000
A8: Industrial projects | B8: 0 | C8: 1 | D8: 1 | E8: 1 | F8: 2 | G8: 2 | H8: 2 | I8: 3
A9: Industrial avg value | B9: 3200000 | C9: 3200000 | D9: 3200000 | E9: 3200000 | F9: 3200000 | G9: 3200000 | H9: 3200000 | I9: 3200000
A10: Revenue | B10: =B4*B5+B6*B7+B8*B9 | C10: =C4*C5+C6*C7+C8*C9 | D10: =D4*D5+D6*D7+D8*D9 | E10: =E4*E5+E6*E7+E8*E9 | F10: =F4*F5+F6*F7+F8*F9 | G10: =G4*G5+G6*G7+G8*G9 | H10: =H4*H5+H6*H7+H8*H9 | I10: =I4*I5+I6*I7+I8*I9

Sheet Labor
A1: Ironwood Construction Co. - Labour
A2: Field crews and site supervision. Wage figures are fully-loaded cost per head per quarter, including burden.
A3: Quarter | B3: Q1 2026 | C3: Q2 2026 | D3: Q3 2026 | E3: Q4 2026 | F3: Q1 2027 | G3: Q2 2027 | H3: Q3 2027 | I3: Q4 2027
A4: Field crew headcount | B4: 38 | C4: 42 | D4: 46 | E4: 50 | F4: 56 | G4: 60 | H4: 66 | I4: 72
A5: Cost per crew / qtr | B5: 18500 | C5: 18500 | D5: 19000 | E5: 19000 | F5: 19600 | G5: 19600 | H5: 20200 | I5: 20200
A6: Site supervisors | B6: 6 | C6: 6 | D6: 7 | E6: 7 | F6: 8 | G6: 8 | H6: 9 | I6: 10
A7: Cost per supervisor / qtr | B7: 31000 | C7: 31000 | D7: 31000 | E7: 31000 | F7: 31000 | G7: 31000 | H7: 31000 | I7: 31000
A8: Total labour cost | B8: =B4*B5+B6*B7 | C8: =C4*C5+C6*C7 | D8: =D4*D5+D6*D7 | E8: =E4*E5+E6*E7 | F8: =F4*F5+F6*F7 | G8: =G4*G5+G6*G7 | H8: =H4*H5+H6*H7 | I8: =I4*I5+I6*I7

Sheet Equipment
A1: Ironwood Construction Co. - Equipment
A2: Owned plant, short-term rentals and running costs for the fleet.
A3: Quarter | B3: Q1 2026 | C3: Q2 2026 | D3: Q3 2026 | E3: Q4 2026 | F3: Q1 2027 | G3: Q2 2027 | H3: Q3 2027 | I3: Q4 2027
A4: Owned fleet depreciation | B4: 95000 | C4: 95000 | D4: 110000 | E4: 110000 | F4: 128000 | G4: 128000 | H4: 128000 | I4: 140000
A5: Equipment rental | B5: 60000 | C5: 72000 | D5: 88000 | E5: 70000 | F5: 95000 | G5: 110000 | H5: 98000 | I5: 120000
A6: Fuel & maintenance | B6: 41000 | C6: 46000 | D6: 52000 | E6: 55000 | F6: 63000 | G6: 68000 | H6: 74000 | I6: 82000
A7: Total equipment cost | B7: =SUM(B4:B6) | C7: =SUM(C4:C6) | D7: =SUM(D4:D6) | E7: =SUM(E4:E6) | F7: =SUM(F4:F6) | G7: =SUM(G4:G6) | H7: =SUM(H4:H6) | I7: =SUM(I4:I6)

Sheet Materials
A1: Ironwood Construction Co. - Materials
A2: Direct materials purchased for active residential and commercial jobs, before retentions.
A3: Quarter | B3: Q1 2026 | C3: Q2 2026 | D3: Q3 2026 | E3: Q4 2026 | F3: Q1 2027 | G3: Q2 2027 | H3: Q3 2027 | I3: Q4 2027
A4: Concrete & aggregate | B4: 310000 | C4: 355000 | D4: 420000 | E4: 470000 | F4: 540000 | G4: 590000 | H4: 660000 | I4: 730000
A5: Steel & rebar | B5: 180000 | C5: 205000 | D5: 250000 | E5: 280000 | F5: 330000 | G5: 360000 | H5: 410000 | I5: 460000
A6: Lumber & framing | B6: 240000 | C6: 275000 | D6: 320000 | E6: 360000 | F6: 410000 | G6: 450000 | H6: 500000 | I6: 560000
A7: Finishes & fixtures | B7: 160000 | C7: 185000 | D7: 215000 | E7: 245000 | F7: 285000 | G7: 315000 | H7: 355000 | I7: 400000
A8: Total materials cost | B8: =SUM(B4:B7) | C8: =SUM(C4:C7) | D8: =SUM(D4:D7) | E8: =SUM(E4:E7) | F8: =SUM(F4:F7) | G8: =SUM(G4:G7) | H8: =SUM(H4:H7) | I8: =SUM(I4:I7)

Sheet Overhead
A1: Ironwood Construction Co. - Overhead
A2: Indirect costs: head-office staff, premises, insurance, bonding and the estimating team that prepares competitive bids.
A3: Quarter | B3: Q1 2026 | C3: Q2 2026 | D3: Q3 2026 | E3: Q4 2026 | F3: Q1 2027 | G3: Q2 2027 | H3: Q3 2027 | I3: Q4 2027
A4: Admin & office headcount | B4: 9 | C4: 9 | D4: 10 | E4: 11 | F4: 12 | G4: 12 | H4: 13 | I4: 14
A5: Admin staff costs | B5: =B4*16500 | C5: =C4*16500 | D5: =D4*16500 | E5: =E4*16500 | F5: =F4*16500 | G5: =G4*16500 | H5: =H4*16500 | I5: =I4*16500
A6: Office, rent & utilities | B6: 48000 | C6: 48000 | D6: 52000 | E6: 52000 | F6: 57000 | G6: 57000 | H6: 62000 | I6: 62000
A7: Insurance & bonding | B7: 72000 | C7: 78000 | D7: 85000 | E7: 92000 | F7: 101000 | G7: 109000 | H7: 118000 | I7: 128000
A8: Marketing & bid prep | B8: 35000 | C8: 40000 | D8: 38000 | E8: 44000 | F8: 42000 | G8: 48000 | H8: 46000 | I8: 52000
A9: Total overhead | B9: =B5+B6+B7+B8 | C9: =C5+C6+C7+C8 | D9: =D5+D6+D7+D8 | E9: =E5+E6+E7+E8 | F9: =F5+F6+F7+F8 | G9: =G5+G6+G7+G8 | H9: =H5+H6+H7+H8 | I9: =I5+I6+I7+I8
